tree_ring_watermark/__init__.py
tree_ring_watermark/_check.py
tree_ring_watermark/_detect.py
tree_ring_watermark/_get_noise.py
tree_ring_watermark/dependency_versions_table.py
tree_ring_watermark-0.0.2.dist-info/LICENSE.md
tree_ring_watermark-0.0.2.dist-info/METADATA
tree_ring_watermark-0.0.2.dist-info/WHEEL
tree_ring_watermark-0.0.2.dist-info/top_level.txt
tree_ring_watermark-0.0.2.dist-info/RECORD
