Metadata-Version: 2.1
Name: tree-ring-watermark
Version: 0.0.2
Summary: tree_ring_watermark
Home-page: https://github.com/YuxinWenRick/tree-ring-watermark
Author: Yuxin Wen
Author-email: patrick@huggingface.co
License: MIT
Keywords: deep learning
Platform: UNKNOWN
Classifier: Development Status :: 5 - Production/Stable
Classifier: Intended Audience :: Developers
Classifier: Intended Audience :: Education
Classifier: Intended Audience :: Science/Research
Classifier: License :: OSI Approved :: Apache Software License
Classifier: Operating System :: OS Independent
Classifier: Programming Language :: Python :: 3
Classifier: Programming Language :: Python :: 3.7
Classifier: Programming Language :: Python :: 3.8
Classifier: Programming Language :: Python :: 3.9
Classifier: Topic :: Scientific/Engineering :: Artificial Intelligence
Requires-Python: >=3.7.0
License-File: LICENSE.md
Requires-Dist: diffusers (==0.11.1)
Requires-Dist: torch (==1.13.0)
Requires-Dist: transformers (==4.23.1)
